onms_kafka_events/__init__.py
onms_kafka_events/kafka_consumer_events_pb2.py
onms_kafka_events-1.0.0.dist-info/LICENSE.txt
onms_kafka_events-1.0.0.dist-info/METADATA
onms_kafka_events-1.0.0.dist-info/WHEEL
onms_kafka_events-1.0.0.dist-info/top_level.txt
onms_kafka_events-1.0.0.dist-info/RECORD
