Metadata-Version: 2.1
Name: onms-kafka-events
Version: 1.0.0
Summary: A Python library for sending events via kafka_consumer to OpenNMS.
Author-email: Mark Mahacek <mmahacek@opennms.com>
License: MIT License
Project-URL: Homepage, https://github.com/opennms-forge/kafka-consumer-py
Project-URL: Documentation, https://opennms-forge.github.io/kafka-consumer-py/
Classifier: Programming Language :: Python :: 3.7
Classifier: Programming Language :: Python :: 3.8
Classifier: Programming Language :: Python :: 3.9
Classifier: Programming Language :: Python :: 3.10
Classifier: License :: OSI Approved :: MIT License
Classifier: Operating System :: OS Independent
Classifier: Development Status :: 5 - Production/Stable
Classifier: Intended Audience :: Information Technology
Classifier: Intended Audience :: System Administrators
Classifier: Intended Audience :: Developers
Classifier: Natural Language :: English
Requires-Python: >=3.7
License-File: LICENSE.txt
Requires-Dist: kafka-python
Requires-Dist: protobuf
